ligttools/__init__.py
ligttools/convert.py
ligttools/search.py
ligttools/serve.py
ligttools/converters/__init__.py
ligttools/converters/base.py
ligttools/converters/cldf_converter.py
ligttools/converters/flex_converter.py
ligttools/converters/glottolog-codes.txt
ligttools/converters/toolbox_converter.py
ligttools/query/__init__.py
ligttools/query/sparql.py
ligttools-0.3.1.dist-info/METADATA
ligttools-0.3.1.dist-info/WHEEL
ligttools-0.3.1.dist-info/entry_points.txt
ligttools-0.3.1.dist-info/licenses/LICENSE
ligttools-0.3.1.dist-info/RECORD
