Metadata-Version: 2.4
Name: ligttools
Version: 0.3.1
Summary: Tools for converting and searching data between different formats and RDF specification
Project-URL: Homepage, https://github.com/ligt-dev/ligttools
Project-URL: Issues, https://github.com/ligt-dev/ligttools/issues
Author-email: Max Ionov <max.ionov@gmail.com>
License: MIT
License-File: LICENSE
Classifier: Development Status :: 4 - Beta
Classifier: Intended Audience :: Developers
Classifier: Intended Audience :: Science/Research
Classifier: Operating System :: OS Independent
Classifier: Programming Language :: Python :: 3
Classifier: Topic :: File Formats
Requires-Python: >=3.9
Requires-Dist: cldflex>=0.1.0
Requires-Dist: flask>=3.1.2
Requires-Dist: numpy>=1.25
Requires-Dist: oxrdflib>=0.4.0
Requires-Dist: pandas>=2.2
Requires-Dist: pycldf>=1.41.0
Requires-Dist: rdflib>=6.3.2
Requires-Dist: requests>=2.32.3
Requires-Dist: writio>=0.1.2
Provides-Extra: dev
Requires-Dist: pytest>=7.0.0; extra == 'dev'
